desktop_file_generator/__init__.py
desktop_file_generator/create_desktop_file.py
desktop_file_generator-0.0.3.dist-info/METADATA
desktop_file_generator-0.0.3.dist-info/WHEEL
desktop_file_generator-0.0.3.dist-info/licenses/LICENSE
desktop_file_generator-0.0.3.dist-info/RECORD
