Metadata-Version: 2.3
Name: desktop_file_generator
Version: 0.0.3
Summary: Automate the creation of .desktop files for the Linux desktop
Project-URL: Homepage, https://github.com/cmbryan/desktop_file_generator
Project-URL: Issues, https://github.com/cmbryan/desktop_file_generator/issues
Author-email: Chris Bryan <chrismbryan@gmail.com>
License:                                  Apache License
License-File: LICENSE
Classifier: License :: OSI Approved :: Apache Software License
Classifier: Operating System :: OS Independent
Classifier: Programming Language :: Python :: 3
Requires-Python: >=3.8
